dbesg/__init__.py
dbesg/utils.py
dbesg/yieldcurve.py
dbesg-0.0.4.dist-info/LICENSE
dbesg-0.0.4.dist-info/METADATA
dbesg-0.0.4.dist-info/WHEEL
dbesg-0.0.4.dist-info/top_level.txt
dbesg-0.0.4.dist-info/RECORD
