Metadata-Version: 2.1
Name: dbesg
Version: 0.0.4
Summary: Economic Scenario Generator
Home-page: https://github.com/lee3jjang/dbesg
Author: Lee Sang Jin
Author-email: lee3jjang@gmail.com
License: UNKNOWN
Platform: UNKNOWN
Classifier: Programming Language :: Python :: 3
Classifier: License :: OSI Approved :: MIT License
Classifier: Operating System :: OS Independent
